[{"volume":2105,"rolling7DayVolume":14390,"weekToWeekChangeVolume":2215,"changePercentage":-6,"margin":3943,"rum":1.8035710279,"date":"2023-12-16T00:00:00.000","stationNumber":99723},{"volume":2164,"rolling7DayVolume":14767,"weekToWeekChangeVolume":1066,"changePercentage":6,"margin":3319,"rum":1.38152769,"date":"2023-12-17T00:00:00.000","stationNumber":99723},{"volume":2387,"rolling7DayVolume":15418,"weekToWeekChangeVolume":1544,"changePercentage":-7,"margin":4171,"rum":1.6214353851,"date":"2023-12-18T00:00:00.000","stationNumber":99723},{"volume":2484,"rolling7DayVolume":15890,"weekToWeekChangeVolume":1484,"changePercentage":5,"margin":3008,"rum":1.5781324724,"date":"2023-12-19T00:00:00.000","stationNumber":99723},{"volume":2417,"rolling7DayVolume":14428,"weekToWeekChangeVolume":2219,"changePercentage":0,"margin":5252,"rum":1.4998418954,"date":"2023-12-20T00:00:00.000","stationNumber":99723},{"volume":2207,"rolling7DayVolume":13160,"weekToWeekChangeVolume":1188,"changePercentage":1,"margin":4069,"rum":1.3039970189,"date":"2023-12-21T00:00:00.000","stationNumber":99723},{"volume":2120,"rolling7DayVolume":15577,"weekToWeekChangeVolume":1208,"changePercentage":6,"margin":4375,"rum":1.6090512729,"date":"2023-12-22T00:00:00.000","stationNumber":99723},{"volume":2251,"rolling7DayVolume":15771,"weekToWeekChangeVolume":1873,"changePercentage":7,"margin":4653,"rum":1.4309491848,"date":"2023-12-23T00:00:00.000","stationNumber":99723},{"volume":2322,"rolling7DayVolume":16210,"weekToWeekChangeVolume":1043,"changePercentage":-6,"margin":3990,"rum":1.7632448804,"date":"2023-12-24T00:00:00.000","stationNumber":99723},{"volume":2275,"rolling7DayVolume":14572,"weekToWeekChangeVolume":1158,"changePercentage":-5,"margin":3155,"rum":1.8178572331,"date":"2023-12-25T00:00:00.000","stationNumber":99723},{"volume":2370,"rolling7DayVolume":13512,"weekToWeekChangeVolume":2063,"changePercentage":-8,"margin":5132,"rum":1.5737103713,"date":"2023-12-26T00:00:00.000","stationNumber":99723},{"volume":2258,"rolling7DayVolume":14287,"weekToWeekChangeVolume":1492,"changePercentage":7,"margin":3677,"rum":1.4679339182,"date":"2023-12-27T00:00:00.000","stationNumber":99723},{"volume":2468,"rolling7DayVolume":11931,"weekToWeekChangeVolume":1052,"changePercentage":7,"margin":3701,"rum":1.8376186867,"date":"2023-12-28T00:00:00.000","stationNumber":99723},{"volume":2264,"rolling7DayVolume":11889,"weekToWeekChangeVolume":1288,"changePercentage":-2,"margin":3985,"rum":1.4546485946,"date":"2023-12-29T00:00:00.000","stationNumber":99723},{"volume":2238,"rolling7DayVolume":11538,"weekToWeekChangeVolume":1114,"changePercentage":-4,"margin":3144,"rum":1.4238504384,"date":"2023-12-30T00:00:00.000","stationNumber":99723},{"volume":2471,"rolling7DayVolume":14628,"weekToWeekChangeVolume":1537,"changePercentage":-6,"margin":4313,"rum":1.3117292603,"date":"2023-12-31T00:00:00.000","stationNumber":99723},{"volume":2059,"rolling7DayVolume":13265,"weekToWeekChangeVolume":1142,"changePercentage":6,"margin":3240,"rum":1.3581805087,"date":"2024-01-01T00:00:00.000","stationNumber":99723},{"volume":2309,"rolling7DayVolume":16672,"weekToWeekChangeVolume":1289,"changePercentage":6,"margin":5018,"rum":1.8138546627,"date":"2024-01-02T00:00:00.000","stationNumber":99723}]